setup.py
otis/__init__.py
otis/proto/__init__.py
otis/proto/otis_pb2.py
otis_proto.egg-info/PKG-INFO
otis_proto.egg-info/SOURCES.txt
otis_proto.egg-info/dependency_links.txt
otis_proto.egg-info/requires.txt
otis_proto.egg-info/top_level.txt