Metadata-Version: 1.0
Name: otis-proto
Version: 0.0.1
Summary: Open Timeseries Interface Service protobuf bindings
Home-page: https://github.com/hodgesds/otis-proto/python
Author: Daniel Hodges
Author-email: hodges.daniel.scott@gmail.com
License: UNKNOWN
Platform: UNKNOWN
